{"name":"lisbon-public-buildings","title":"Lisbon Public Buildings","description":"Electricity consumption from 15 to 15 min of 92 installations pertaining to CML with LV and MV contracts referring to the period between Jan/13 and Dec/15.\r\nSource: http://dados.cm-lisboa.pt/dataset/consumoseletricosedificioscml-2013-15","licenses":[{"url":"https://creativecommons.org/licenses/by/4.0/","title":"Creative Commons Attribution 4.0"}],"publishers":[{"name":"IN+","web":"https://github.com/INmais"}],"resources":[{"name":"6516363 - Casa_dos_Bicos","mediatype":"text/csv","description":"6516363 - Casa_dos_Bicos","path":"data/6516363-casa_dos_bicos.csv"},{"name":"4046417 - Posto_de_Limpeza","mediatype":"text/csv","description":"4046417 - Posto_de_Limpeza","path":"data/4046417-posto_de_limpeza.csv"},{"name":"6516444_Gab_de_apoio_vereacao.csv","mediatype":"text/csv","description":"6516444_Gab_de_apoio_vereacao.csv","path":"data/6516444_gab_de_apoio_vereacao-csv.csv"},{"name":"6516815_Biblioteca_de_estudos_Olisiponeneses.csv","mediatype":"text/csv","description":"6516815_Biblioteca_de_estudos_Olisiponeneses.csv","path":"data/6516815_biblioteca_de_estudos_olisiponeneses-csv.csv"},{"name":"6516981_Videoteca_municipal.csv","mediatype":"text/csv","description":"6516981_Videoteca_municipal.csv","path":"data/6516981_videoteca_municipal-csv.csv"},{"name":"10012776 - Biblioteca","mediatype":"text/csv","description":"10012776 - Biblioteca","path":"data/10012776-biblioteca.csv"},{"name":"10017322 - Laboratório de Bromatologia","mediatype":"text/csv","description":"10017322 - Laboratório de Bromatologia","path":"data/10017322-laboratorio-de-bromatologia.csv"}]}